{
  "notes": [
    {
      "id": 1,
      "body": "Todays Agenda\n\n- Walk Dog\n- Feed fish\n- Play basketball\n- Eat a salad\n- bruh",
      "updated": "2022-07-18T13:59:07.356Z",
      "created": "2021-07-13T21:54:16.235392Z"
    },
    {
      "id": 2,
      "body": "Bob from bar down the ffff\n\n- Take out trash\n- Eat food",
      "updated": "2022-07-18T09:09:07.537Z",
      "created": "2021-07-13T00:17:13.289897Z"
    },
    {
      "body": "somethingasssssdawdasdadasxcsdeffcwsaefadfvsdfvszadv",
      "updated": "2022-07-18T09:08:58.781Z",
      "id": 3
    },
    {
      "body": "o",
      "updated": "2022-07-18T14:04:30.288Z",
      "id": 18
    },
    {
      "body": "p",
      "updated": "2022-07-18T08:55:44.246Z",
      "id": 19
    },
    {
      "body": "q",
      "updated": "2022-07-18T08:55:46.756Z",
      "id": 20
    },
    {
      "body": "r",
      "updated": "2022-07-18T13:45:04.177Z",
      "id": 21
    },
    {
      "body": "s",
      "updated": "2022-07-18T14:05:18.561Z",
      "id": 22
    },
    {
      "body": "asdasd",
      "updated": "2022-07-18T14:05:58.850Z",
      "id": 23
    }
  ]
}